{
	"info": {
		"_postman_id": "megastore-api-2026",
		"name": "MegaStore API",
		"description": "Colección para probar la API con PostgreSQL y MongoDB",
		"schema": "https://schema.getpostman.com/json/collection/v2.1.0/collection.json"
	},
	"item": [
		{
			"name": "Products",
			"item": [
				{
					"name": "1. GET All Products",
					"request": {
						"method": "GET",
						"header": [],
						"url": {
							"raw": "{{base_url}}/api/products",
							"host": [
								"{{base_url}}"
							],
							"path": [
								"api",
								"products"
							]
						},
						"description": "Obtiene todos los productos del catálogo"
					},
					"response": []
				},
				{
					"name": "2. GET Product by ID",
					"request": {
						"method": "GET",
						"header": [],
						"url": {
							"raw": "{{base_url}}/api/products/1",
							"host": [
								"{{base_url}}"
							],
							"path": [
								"api",
								"products",
								"1"
							]
						},
						"description": "Obtiene un producto específico por su ID"
					},
					"response": []
				},
				{
					"name": "3. POST Create Product",
					"request": {
						"method": "POST",
						"header": [
							{
								"key": "Content-Type",
								"value": "application/json"
							}
						],
						"body": {
							"mode": "raw",
							"raw": "{\n  \"sku\": \"TEST-001\",\n  \"name\": \"Producto de Prueba\",\n  \"description\": \"Descripción del producto de prueba\",\n  \"unit_price\": 99.99,\n  \"stock_quantity\": 100,\n  \"category_id\": 1,\n  \"supplier_id\": 1\n}"
						},
						"url": {
							"raw": "{{base_url}}/api/products",
							"host": [
								"{{base_url}}"
							],
							"path": [
								"api",
								"products"
							]
						},
						"description": "Crea un nuevo producto en el catálogo"
					},
					"response": []
				},
				{
					"name": "4. PUT Update Product",
					"request": {
						"method": "PUT",
						"header": [
							{
								"key": "Content-Type",
								"value": "application/json"
							}
						],
						"body": {
							"mode": "raw",
							"raw": "{\n  \"name\": \"Producto Actualizado\",\n  \"description\": \"Descripción actualizada\",\n  \"unit_price\": 149.99,\n  \"stock_quantity\": 75\n}"
						},
						"url": {
							"raw": "{{base_url}}/api/products/1",
							"host": [
								"{{base_url}}"
							],
							"path": [
								"api",
								"products",
								"1"
							]
						},
						"description": "Actualiza un producto existente"
					},
					"response": []
				},
				{
					"name": "5. DELETE Product",
					"request": {
						"method": "DELETE",
						"header": [],
						"url": {
							"raw": "{{base_url}}/api/products/1",
							"host": [
								"{{base_url}}"
							],
							"path": [
								"api",
								"products",
								"1"
							]
						},
						"description": "Elimina un producto y registra el audit log en MongoDB"
					},
					"response": []
				},
				{
					"name": "6. GET Product Audit Logs",
					"request": {
						"method": "GET",
						"header": [],
						"url": {
							"raw": "{{base_url}}/api/products/audit/1",
							"host": [
								"{{base_url}}"
							],
							"path": [
								"api",
								"products",
								"audit",
								"1"
							]
						},
						"description": "Obtiene el historial de auditoría de un producto específico desde MongoDB"
					},
					"response": []
				}
			],
			"description": "Operaciones CRUD para productos"
		},
		{
			"name": "Analytics",
			"item": [
				{
					"name": "7. GET Supplier Analysis",
					"request": {
						"method": "GET",
						"header": [],
						"url": {
							"raw": "{{base_url}}/api/analytics/suppliers",
							"host": [
								"{{base_url}}"
							],
							"path": [
								"api",
								"analytics",
								"suppliers"
							]
						},
						"description": "Análisis de proveedores: productos en catálogo, items vendidos y valor total de ventas"
					},
					"response": []
				},
				{
					"name": "8. GET Customer History",
					"request": {
						"method": "GET",
						"header": [],
						"url": {
							"raw": "{{base_url}}/api/analytics/customers/1/history",
							"host": [
								"{{base_url}}"
							],
							"path": [
								"api",
								"analytics",
								"customers",
								"1",
								"history"
							]
						},
						"description": "Historial completo de compras de un cliente específico"
					},
					"response": []
				},
				{
					"name": "9. GET Top Products by Category",
					"request": {
						"method": "GET",
						"header": [],
						"url": {
							"raw": "{{base_url}}/api/analytics/products/top-by-category/Electronics",
							"host": [
								"{{base_url}}"
							],
							"path": [
								"api",
								"analytics",
								"products",
								"top-by-category",
								"Electronics"
							]
						},
						"description": "Top productos más vendidos en una categoría específica"
					},
					"response": []
				}
			],
			"description": "Consultas analíticas que combinan PostgreSQL y MongoDB"
		}
	],
	"event": [
		{
			"listen": "prerequest",
			"script": {
				"type": "text/javascript",
				"exec": [
					""
				]
			}
		},
		{
			"listen": "test",
			"script": {
				"type": "text/javascript",
				"exec": [
					""
				]
			}
		}
	],
	"variable": [
		{
			"key": "base_url",
			"value": "http://localhost:3000",
			"type": "string"
		}
	]
}
